{
    "fechaUTC": "2025-09-05T20:30:51.5120603Z",
    "duracionSeg": 605.707763671875,
    "generados": 76,
    "despachados": 16,
    "enPila": 59,
    "maxAlturaPila": 60,
    "tiempoPromedioDespacho": 2.5,
    "pesoTotalDespachado": 30.579998016357423,
    "ingresoTotalDespachado": 4422.90966796875,
    "porTipo": [
        {
            "tipo": "Basico",
            "generados": 21,
            "despachados": 5
        },
        {
            "tipo": "Fragil",
            "generados": 23,
            "despachados": 7
        },
        {
            "tipo": "Pesado",
            "generados": 32,
            "despachados": 4
        },
        {
            "tipo": "Otro",
            "generados": 0,
            "despachados": 0
        }
    ]
}